Metadata-Version: 1.2
Name: sdb-officialator
Version: 0.1
Summary: Tools for assigning derby officials to roles.
Home-page: UNKNOWN
Author: Damon May
License: UNKNOWN
Project-URL: Source, https://github.com/dhmay/sdb-officialator
Platform: UNKNOWN
Classifier: Development Status :: 3 - Alpha
Classifier: Programming Language :: Python :: 3
Classifier: Programming Language :: Python :: 3.7
